NeditGD/GroupRange.py
NeditGD/__init__.py
NeditGD/comparator.py
NeditGD/editor_gd.py
NeditGD/example.py
NeditGD/example_all_ids.py
NeditGD/group_remap.py
NeditGD/level_save.py
NeditGD/object_gd.py
NeditGD/properties.py
NeditGD/reader.py
NeditGD/saveload.py
NeditGD/Dictionaries/BooleanID.py
NeditGD/Dictionaries/IDNames.py
NeditGD/Dictionaries/ParticleEmitter.py
NeditGD/Dictionaries/PropertyAlias.py
NeditGD/Dictionaries/PropertyHSV.py
NeditGD/Dictionaries/PropertyID.py
NeditGD/Dictionaries/__init__.py
NeditGD/Dictionaries/logic_IDs.py
NeditGD/Nextra/__init__.py
NeditGD/Nextra/group_pool.py
NeditGD/Nextra/marker_loader.py
NeditGD-0.3.0.dist-info/LICENSE
NeditGD-0.3.0.dist-info/METADATA
NeditGD-0.3.0.dist-info/WHEEL
NeditGD-0.3.0.dist-info/top_level.txt
NeditGD-0.3.0.dist-info/RECORD
