Metadata-Version: 2.1
Name: NeditGD
Version: 0.3.0
Summary: Lightweight Geometry Dash level scripting tool
Home-page: https://github.com/Boris-Filin/NeditGD
Author: Nemo2510 (Boris Filin)
Author-email: oonemoo2510@gmail.com
License: MIT
Requires-Python: >=3.12.0
License-File: LICENSE
Requires-Dist: websocket-client
